{
    "version": "0.9.1",
    "architecture": {
        "32bit": {
            "url": "https://github.com/rsteube/carapace-bin/releases/download/v0.9.1/carapace-bin_0.9.1_Windows_i386.tar.gz",
            "bin": [
                "carapace.exe"
            ],
            "hash": "9a8763d20157f8852827e432a5e718bdd41d7fa2e67253b4bdf2fc7bb248c366"
        },
        "64bit": {
            "url": "https://github.com/rsteube/carapace-bin/releases/download/v0.9.1/carapace-bin_0.9.1_Windows_x86_64.tar.gz",
            "bin": [
                "carapace.exe"
            ],
            "hash": "18e8ea8479f9e8404c4889bc2adfb394dd24ce15353fe14ac76a509b179c3484"
        }
    },
    "homepage": "https://github.com/rsteube/carapace-bin",
    "license": "MIT",
    "description": "multi-shell multi-command argument completer"
}