{
    "version": "0.28.5",
    "architecture": {
        "32bit": {
            "url": "https://github.com/rsteube/carapace-bin/releases/download/v0.28.5/carapace-bin_windows_386.zip",
            "bin": [
                "carapace.exe"
            ],
            "hash": "e40f1320139bc831fc5b0cef8f0ebb524e52626b45168a6292816846e5901f6b"
        },
        "64bit": {
            "url": "https://github.com/rsteube/carapace-bin/releases/download/v0.28.5/carapace-bin_windows_amd64.zip",
            "bin": [
                "carapace.exe"
            ],
            "hash": "6dfe640a1bb1012e70c6e67e9a970ae0f6129e35b176ab947eb9b2276d0ba71e"
        },
        "arm64": {
            "url": "https://github.com/rsteube/carapace-bin/releases/download/v0.28.5/carapace-bin_windows_arm64.zip",
            "bin": [
                "carapace.exe"
            ],
            "hash": "3fd02621c2033a5bc594f0a2462c00047cedd02c6718f840e246cd93ea60fb89"
        }
    },
    "homepage": "https://github.com/rsteube/carapace-bin",
    "license": "MIT",
    "description": "multi-shell multi-command argument completer"
}