{
    "version": "0.24.4",
    "architecture": {
        "32bit": {
            "url": "https://github.com/rsteube/carapace-bin/releases/download/v0.24.4/carapace-bin_windows_386.zip",
            "bin": [
                "carapace.exe"
            ],
            "hash": "b6a21a69432e82dba3af307cbe573784a369906c3969fde86b20f57ce58d26ba"
        },
        "64bit": {
            "url": "https://github.com/rsteube/carapace-bin/releases/download/v0.24.4/carapace-bin_windows_amd64.zip",
            "bin": [
                "carapace.exe"
            ],
            "hash": "a4b9f462062a134b0a68caf5763ee0e788cb32ba4db6a1ee65618ae573365b7d"
        }
    },
    "homepage": "https://github.com/rsteube/carapace-bin",
    "license": "MIT",
    "description": "multi-shell multi-command argument completer"
}