{
    "version": "0.0.18",
    "architecture": {
        "32bit": {
            "url": "https://github.com/rsteube/lazycomplete/releases/download/v0.0.18/lazycomplete_0.0.18_Windows_i386.tar.gz",
            "bin": [
                "lazycomplete.exe"
            ],
            "hash": "77fecaa43a54e118694e927337e055cc9ae7a5c6831d2672d8168c276025ff6d"
        },
        "64bit": {
            "url": "https://github.com/rsteube/lazycomplete/releases/download/v0.0.18/lazycomplete_0.0.18_Windows_x86_64.tar.gz",
            "bin": [
                "lazycomplete.exe"
            ],
            "hash": "db8696201f1206a861cc9e17546676c20be0e6e5980378359c0037c3036469d4"
        }
    },
    "homepage": "https://github.com/rsteube/lazycomplete",
    "license": "MIT",
    "description": "lazy loading for shell completion scripts"
}